pypoem/__init__.py
pypoem/_version.py
pypoem/pypoem.cp313-win_amd64.pyd
pypoem/tools/__init__.py
pypoem/tools/poem_check.py
pypoem/tools/poem_clean.py
pypoem/tools/poem_hash.py
pypoem/tools/poem_info.py
pypoem/tools/poem_layout.py
pypoem/tools/poem_mount.py
pypoem/tools/poem_tree.py
pypoem/tools/poem_upgrade.py
pypoem/tools/poem_version.py
pypoem/tools/README.txt
pypoem-1.6.11.dist-info/METADATA
pypoem-1.6.11.dist-info/WHEEL
pypoem-1.6.11.dist-info/entry_points.txt
pypoem-1.6.11.dist-info/licenses/LICENSE.txt
pypoem-1.6.11.dist-info/RECORD
