Metadata-Version: 2.2
Name: pypoem
Version: 1.6.11
Summary: Performance pOlar Exchange forMat
Maintainer-Email: D-ICE ENGINEERING <francois.rongere@dice-engineering.com>
Classifier: Topic :: Scientific/Engineering
Classifier: Intended Audience :: Science/Research
Classifier: Intended Audience :: Developers
Classifier: Operating System :: OS Independent
Classifier: Operating System :: Microsoft :: Windows
Classifier: Operating System :: POSIX :: Linux
Classifier: Programming Language :: C++
Classifier: Programming Language :: Python
Classifier: Programming Language :: Python :: 3
Classifier: Programming Language :: Python :: 3 :: Only
Classifier: Programming Language :: Python :: 3.9
Classifier: Programming Language :: Python :: 3.10
Classifier: Programming Language :: Python :: 3.11
Classifier: Programming Language :: Python :: 3.12
Classifier: Programming Language :: Python :: 3.13
Classifier: Development Status :: 4 - Beta
Project-URL: Homepage, https://github.com/D-ICE/poem
Project-URL: Documentation, https://dice-poem.readthedocs.io/en/latest/
Requires-Python: >=3.9
Requires-Dist: argparse
Requires-Dist: sha256
Requires-Dist: pydot
